Workbook

Sheet Legend
A1: College Outreach Engine & Competitor Pricing Study
A3: Yellow cells with blue text = inputs you edit. Black cells = formulas (do not overwrite).
A4: Row 5 of Competitor_Benchmark (Asyvyas) comes from asyvyas.in; fill every other row from each company's own public site and cite the URL.
A5: Example rows in College_Pipeline and Outreach_Log are placeholders - delete or overwrite them.
A6: Tier-scoring weights are on the 'Assumptions' sheet. Change them there and every priority score updates.
A7: Only report response rates from real outreach. Do not present the sample CSV in data/ as real results.

Sheet Assumptions
A1: Parameter | B1: Value | C1: Note
A2: Tier-1 weight | B2: 3 | C2: Higher = more attractive prospect (placement-cell reach, brand)
A3: Tier-2 weight | B3: 2
A4: Tier-3 weight | B4: 1
A5: Strength weight per 1,000 students | B5: 1 | C5: Larger colleges = more potential enrolments
A6: Warm-contact bonus | B6: 2 | C6: Added when we already know someone at the college
A7: Course price incl. GST (INR) | B7: 2949 | C7: Source: asyvyas.in pricing (INR 2,499 + 18% GST)
A8: Assumed enrolment rate per college pitch (%) | B8: 5 | C8: ASSUMPTION - edit once you have real data
A9: Assumed students enrolled per converted college | B9: 20 | C9: ASSUMPTION - edit once you have real data

Sheet Competitor_Benchmark
A1: Company | B1: Primary audience | C1: Example course | D1: Price (INR, incl. GST) | E1: Delivery format | F1: Certification | G1: Placement claim (as stated) | H1: Claim verifiable? (Y/N) | I1: Free trial / demo? | J1: Source URL | K1: Date checked
A2: Fill one row per competitor from its own public pages. Leave unknown cells blank, never guess.
A4: Asyvyas Solutions | B4: College students / freshers | C4: AI & ML, Full Stack, Data Analytics, Cloud, VLSI, Core Engineering (16 tracks listed) | D4: 2949 | E4: 100% live online classes | F4: ISO-certified (as stated on site) | G4: 303,154+ placed students; 4,870+ partner companies (site claim) | H4: N | J4: https://asyvyas.in/ | K4: 19-Oct-2026
A5: NxtWave
A6: Scaler
A7: upGrad
A8: Coursera
A9: Simplilearn
A10: PW Skills
A11: Internshala Trainings
A12: LearnVern / other local
A15: Median price of filled competitors (excl. Asyvyas) | D15: =IF(COUNT(D5:D12)=0,"",MEDIAN(D5:D12))
A16: Asyvyas price vs competitor median | D16: =IF(OR(D15="",D4=""),"",D4/D15-1)
A17: Competitors with unverifiable placement claims | D17: =COUNTIF(H5:H12,"N") -> 0

Sheet College_Pipeline
A1: # | B1: College / institute | C1: City | D1: State | E1: Tier (1/2/3) | F1: Student strength | G1: Warm contact? (Y/N) | H1: T&P contact name | I1: Email / LinkedIn | J1: Stage | K1: Last touch date | L1: Priority score | M1: Priority rank | N1: Notes
A2: 1 | B2: EXAMPLE - replace with a real college | C2: Bengaluru | D2: Karnataka | E2: 2 | F2: 3000 | G2: N | H2: Name of T&P officer | I2: name@college.edu | J2: Not contacted | L2: =IF(OR(B2="",E2=""),"",INDEX(Assumptions!$B$2:$B$4,E2)+Assumptions!$B$5*F2/1000+IF(G2="Y",Assumptions!$B$6,0)) -> 5 | M2: =IF(L2="","",RANK(L2,$L$2:$L$101)) -> 1 | N2: Example row
A3: 2 | L3: =IF(OR(B3="",E3=""),"",INDEX(Assumptions!$B$2:$B$4,E3)+Assumptions!$B$5*F3/1000+IF(G3="Y",Assumptions!$B$6,0)) | M3: =IF(L3="","",RANK(L3,$L$2:$L$101))
A4: 3 | L4: =IF(OR(B4="",E4=""),"",INDEX(Assumptions!$B$2:$B$4,E4)+Assumptions!$B$5*F4/1000+IF(G4="Y",Assumptions!$B$6,0)) | M4: =IF(L4="","",RANK(L4,$L$2:$L$101))
A5: 4 | L5: =IF(OR(B5="",E5=""),"",INDEX(Assumptions!$B$2:$B$4,E5)+Assumptions!$B$5*F5/1000+IF(G5="Y",Assumptions!$B$6,0)) | M5: =IF(L5="","",RANK(L5,$L$2:$L$101))
A6: 5 | L6: =IF(OR(B6="",E6=""),"",INDEX(Assumptions!$B$2:$B$4,E6)+Assumptions!$B$5*F6/1000+IF(G6="Y",Assumptions!$B$6,0)) | M6: =IF(L6="","",RANK(L6,$L$2:$L$101))
A7: 6 | L7: =IF(OR(B7="",E7=""),"",INDEX(Assumptions!$B$2:$B$4,E7)+Assumptions!$B$5*F7/1000+IF(G7="Y",Assumptions!$B$6,0)) | M7: =IF(L7="","",RANK(L7,$L$2:$L$101))
A8: 7 | L8: =IF(OR(B8="",E8=""),"",INDEX(Assumptions!$B$2:$B$4,E8)+Assumptions!$B$5*F8/1000+IF(G8="Y",Assumptions!$B$6,0)) | M8: =IF(L8="","",RANK(L8,$L$2:$L$101))
A9: 8 | L9: =IF(OR(B9="",E9=""),"",INDEX(Assumptions!$B$2:$B$4,E9)+Assumptions!$B$5*F9/1000+IF(G9="Y",Assumptions!$B$6,0)) | M9: =IF(L9="","",RANK(L9,$L$2:$L$101))
A10: 9 | L10: =IF(OR(B10="",E10=""),"",INDEX(Assumptions!$B$2:$B$4,E10)+Assumptions!$B$5*F10/1000+IF(G10="Y",Assumptions!$B$6,0)) | M10: =IF(L10="","",RANK(L10,$L$2:$L$101))
A11: 10 | L11: =IF(OR(B11="",E11=""),"",INDEX(Assumptions!$B$2:$B$4,E11)+Assumptions!$B$5*F11/1000+IF(G11="Y",Assumptions!$B$6,0)) | M11: =IF(L11="","",RANK(L11,$L$2:$L$101))
A12: 11 | L12: =IF(OR(B12="",E12=""),"",INDEX(Assumptions!$B$2:$B$4,E12)+Assumptions!$B$5*F12/1000+IF(G12="Y",Assumptions!$B$6,0)) | M12: =IF(L12="","",RANK(L12,$L$2:$L$101))
A13: 12 | L13: =IF(OR(B13="",E13=""),"",INDEX(Assumptions!$B$2:$B$4,E13)+Assumptions!$B$5*F13/1000+IF(G13="Y",Assumptions!$B$6,0)) | M13: =IF(L13="","",RANK(L13,$L$2:$L$101))
A14: 13 | L14: =IF(OR(B14="",E14=""),"",INDEX(Assumptions!$B$2:$B$4,E14)+Assumptions!$B$5*F14/1000+IF(G14="Y",Assumptions!$B$6,0)) | M14: =IF(L14="","",RANK(L14,$L$2:$L$101))
... A101: 100 | L101: =IF(OR(B101="",E101=""),"",INDEX(Assumptions!$B$2:$B$4,E101)+Assumptions!$B$5*F101/1000+IF(G101="Y",Assumptions!$B$6,0)) | M101: =IF(L101="","",RANK(L101,$L$2:$L$101))

Sheet Pipeline_Summary
A1: Stage | B1: Colleges | C1: % of contacted
A2: Not contacted | B2: =COUNTIF(College_Pipeline!$J$2:$J$101,A2) -> 1
A3: Touch 1 sent | B3: =COUNTIF(College_Pipeline!$J$2:$J$101,A3) -> 0 | C3: =IF(SUM($B$3:$B$10)=0,"",B3/SUM($B$3:$B$10))
A4: Touch 2 sent | B4: =COUNTIF(College_Pipeline!$J$2:$J$101,A4) -> 0 | C4: =IF(SUM($B$3:$B$10)=0,"",B4/SUM($B$3:$B$10))
A5: Touch 3 sent | B5: =COUNTIF(College_Pipeline!$J$2:$J$101,A5) -> 0 | C5: =IF(SUM($B$3:$B$10)=0,"",B5/SUM($B$3:$B$10))
A6: Replied | B6: =COUNTIF(College_Pipeline!$J$2:$J$101,A6) -> 0 | C6: =IF(SUM($B$3:$B$10)=0,"",B6/SUM($B$3:$B$10))
A7: Meeting booked | B7: =COUNTIF(College_Pipeline!$J$2:$J$101,A7) -> 0 | C7: =IF(SUM($B$3:$B$10)=0,"",B7/SUM($B$3:$B$10))
A8: Pitched | B8: =COUNTIF(College_Pipeline!$J$2:$J$101,A8) -> 0 | C8: =IF(SUM($B$3:$B$10)=0,"",B8/SUM($B$3:$B$10))
A9: Pilot / drive agreed | B9: =COUNTIF(College_Pipeline!$J$2:$J$101,A9) -> 0 | C9: =IF(SUM($B$3:$B$10)=0,"",B9/SUM($B$3:$B$10))
A10: Closed - lost | B10: =COUNTIF(College_Pipeline!$J$2:$J$101,A10) -> 0 | C10: =IF(SUM($B$3:$B$10)=0,"",B10/SUM($B$3:$B$10))
A12: Total colleges listed | B12: =COUNTA(College_Pipeline!$B$2:$B$101) -> 1
A13: Reply rate (replied or beyond / contacted) | B13: =IF(SUM(B3:B10)=0,"",SUM(B6:B9)/SUM(B3:B10))
A15: Illustrative revenue potential (uses Assumptions sheet - ASSUMPTIONS, not forecasts)
A16: Expected converted colleges | B16: =B12*Assumptions!B8/100 -> 0.05
A17: Expected enrolments | B17: =B16*Assumptions!B9 -> 1
A18: Expected revenue (INR) | B18: =B17*Assumptions!B7 -> 2949

Sheet Outreach_Log
A1: Send # | B1: College | C1: Contact | D1: Channel (Email/LinkedIn/WhatsApp) | E1: Variant (A/B) | F1: Date sent | G1: Replied (Y/N) | H1: Meeting booked (Y/N) | I1: Notes
A2: 1 | B2: EXAMPLE - replace with a real college | C2: Name of T&P officer | D2: Email | E2: A | G2: N | H2: N | I2: Example row
A3: 2
A4: 3
A5: 4
A6: 5
A7: 6
A8: 7
A9: 8
A10: 9
A11: 10
A12: 11
A13: 12
A14: 13
... A301: 300

Sheet AB_Summary
A1: Metric | B1: Variant A | C1: Variant B
A2: Messages sent | B2: =COUNTIFS(Outreach_Log!$E$2:$E$301,"A",Outreach_Log!$B$2:$B$301,"<>") -> 1 | C2: =COUNTIFS(Outreach_Log!$E$2:$E$301,"B",Outreach_Log!$B$2:$B$301,"<>") -> 0
A3: Replies | B3: =COUNTIFS(Outreach_Log!$E$2:$E$301,"A",Outreach_Log!$G$2:$G$301,"Y") -> 0 | C3: =COUNTIFS(Outreach_Log!$E$2:$E$301,"B",Outreach_Log!$G$2:$G$301,"Y") -> 0
A4: Reply rate | B4: =IF(B2=0,"",B3/B2) -> 0 | C4: =IF(C2=0,"",C3/C2)
A5: Meetings booked | B5: =COUNTIFS(Outreach_Log!$E$2:$E$301,"A",Outreach_Log!$H$2:$H$301,"Y") -> 0 | C5: =COUNTIFS(Outreach_Log!$E$2:$E$301,"B",Outreach_Log!$H$2:$H$301,"Y") -> 0
A6: Meeting rate | B6: =IF(B2=0,"",B5/B2) -> 0 | C6: =IF(C2=0,"",C5/C2)
A8: Two-proportion z-test on reply rate (A vs B)
A9: Pooled reply rate | B9: =IF(B2+C2=0,"",(B3+C3)/(B2+C2)) -> 0
A10: z statistic | B10: =IF(OR(B2=0,C2=0,B9=""),"",IF(OR(B9=0,B9=1),"",(B4-C4)/SQRT(B9*(1-B9)*(1/B2+1/C2))))
A11: p-value (two-sided) | B11: =IF(B10="","",2*(1-NORMSDIST(ABS(B10))))
A12: Read-out | B12: =IF(B11="","Need sends in both variants",IF(B11<0.05,"Statistically significant at 5%","Not significant - more sends needed")) -> Need sends in both variants
A14: Note: with fewer than ~30 sends per variant the test has very little power; report this honestly.
